AUTHORS.rst
CONTRIBUTING.rst
LICENSE
MANIFEST.in
README.rst
setup.cfg
setup.py
docs/Makefile
docs/make.bat
docs/examples/README.rst
docs/source/conf.py
docs/source/index.rst
docs/source/installation.rst
docs/source/min_versions.rst
docs/source/auto_gallery/index.rst
pdffitx/__init__.py
pdffitx.egg-info/PKG-INFO
pdffitx.egg-info/SOURCES.txt
pdffitx.egg-info/dependency_links.txt
pdffitx.egg-info/entry_points.txt
pdffitx.egg-info/top_level.txt