Metadata-Version: 1.2
Name: pdffitx
Version: 0.0.0
Summary: A python package to model atomic pair distribution function (PDF) based on diffpy-cmi.
Home-page: https://github.com/st3107/pdffitx
Author: Songsheng Tao
Author-email: st3107@columbia.edu
License: BSD (3-clause)
Platform: UNKNOWN
Classifier: Development Status :: 2 - Pre-Alpha
Classifier: Natural Language :: English
Classifier: Programming Language :: Python :: 3
Requires-Python: >=3.7
